BaolingxinTaluoDailingniKaiqiZhijuede78tangTaluoke/README.md
BaolingxinTaluoDailingniKaiqiZhijuede78tangTaluoke/__init__.py
BaolingxinTaluoDailingniKaiqiZhijuede78tangTaluoke/__main__.py
BaolingxinTaluoDailingniKaiqiZhijuede78tangTaluoke/file.pdf
BaolingxinTaluoDailingniKaiqiZhijuede78tangTaluoke/index.html
baolingxin_taluo_dailingni_kaiqi_zhijuede_78tang_taluoke-2022.9.29.0.dist-info/METADATA
baolingxin_taluo_dailingni_kaiqi_zhijuede_78tang_taluoke-2022.9.29.0.dist-info/WHEEL
baolingxin_taluo_dailingni_kaiqi_zhijuede_78tang_taluoke-2022.9.29.0.dist-info/entry_points.txt
baolingxin_taluo_dailingni_kaiqi_zhijuede_78tang_taluoke-2022.9.29.0.dist-info/top_level.txt
baolingxin_taluo_dailingni_kaiqi_zhijuede_78tang_taluoke-2022.9.29.0.dist-info/RECORD
